Metadata-Version: 2.1
Name: pb-distr
Version: 1.0
Summary: Gaussian and Binomial distributions
Home-page: UNKNOWN
Author: Weijie Wang
Author-email: wang.weijie0110@gmail.com
License: UNKNOWN
Platform: UNKNOWN
